pyxro/__init__.py
pyxro/calculation.py
pyxro/defaults.py
pyxro/multilayer.py
pyxro/data/atominfo.json
pyxro/data/binding_energies.csv
pyxro/data/corelevel_data.csv
pyxro/data/formula_data.csv
pyxro/data/acs/Ac.csv
pyxro/data/acs/Ac3d.txt
pyxro/data/acs/Ac3p.txt
pyxro/data/acs/Ac3s.txt
pyxro/data/acs/Ac4d.txt
pyxro/data/acs/Ac4f.txt
pyxro/data/acs/Ac4p.txt
pyxro/data/acs/Ac4s.txt
pyxro/data/acs/Ac5d.txt
pyxro/data/acs/Ac5p.txt
pyxro/data/acs/Ac5s.txt
pyxro/data/acs/Ac6d.txt
pyxro/data/acs/Ac6p.txt
pyxro/data/acs/Ac6s.txt
pyxro/data/acs/Ac7s.txt
pyxro/data/acs/Ag.csv
pyxro/data/acs/Ag2p.txt
pyxro/data/acs/Ag2s.txt
pyxro/data/acs/Ag3d.txt
pyxro/data/acs/Ag3p.txt
pyxro/data/acs/Ag3s.txt
pyxro/data/acs/Ag4d.txt
pyxro/data/acs/Ag4p.txt
pyxro/data/acs/Ag4s.txt
pyxro/data/acs/Ag5s.txt
pyxro/data/acs/Al.csv
pyxro/data/acs/Al1s.txt
pyxro/data/acs/Al2p.txt
pyxro/data/acs/Al2s.txt
pyxro/data/acs/Al3p.txt
pyxro/data/acs/Al3s.txt
pyxro/data/acs/Am.csv
pyxro/data/acs/Am3d.txt
pyxro/data/acs/Am3p.txt
pyxro/data/acs/Am3s.txt
pyxro/data/acs/Am4d.txt
pyxro/data/acs/Am4f.txt
pyxro/data/acs/Am4p.txt
pyxro/data/acs/Am4s.txt
pyxro/data/acs/Am5d.txt
pyxro/data/acs/Am5f.txt
pyxro/data/acs/Am5p.txt
pyxro/data/acs/Am5s.txt
pyxro/data/acs/Am6p.txt
pyxro/data/acs/Am6s.txt
pyxro/data/acs/Am7s.txt
pyxro/data/acs/Ar.csv
pyxro/data/acs/Ar1s.txt
pyxro/data/acs/Ar2p.txt
pyxro/data/acs/Ar2s.txt
pyxro/data/acs/Ar3p.txt
pyxro/data/acs/Ar3s.txt
pyxro/data/acs/As.csv
pyxro/data/acs/As2p.txt
pyxro/data/acs/As2s.txt
pyxro/data/acs/As3d.txt
pyxro/data/acs/As3p.txt
pyxro/data/acs/As3s.txt
pyxro/data/acs/As4p.txt
pyxro/data/acs/As4s.txt
pyxro/data/acs/At.csv
pyxro/data/acs/At3d.txt
pyxro/data/acs/At3p.txt
pyxro/data/acs/At3s.txt
pyxro/data/acs/At4d.txt
pyxro/data/acs/At4f.txt
pyxro/data/acs/At4p.txt
pyxro/data/acs/At4s.txt
pyxro/data/acs/At5d.txt
pyxro/data/acs/At5p.txt
pyxro/data/acs/At5s.txt
pyxro/data/acs/At6p.txt
pyxro/data/acs/At6s.txt
pyxro/data/acs/Au.csv
pyxro/data/acs/Au3d.txt
pyxro/data/acs/Au3p.txt
pyxro-0.1.0.dist-info/LICENSE
pyxro-0.1.0.dist-info/METADATA
pyxro-0.1.0.dist-info/WHEEL
pyxro-0.1.0.dist-info/top_level.txt
pyxro-0.1.0.dist-info/RECORD
