Metadata-Version: 2.1
Name: pyxro
Version: 0.1.0
Summary: x-ray optics package
Author-email: Henrique Martins <hpmartins@gmail.com>
License: MLExchange Copyright (c) 2023, The Regents of the University of California,
Project-URL: Homepage, https://github.com/mlexchange/mlex_pyxro
Classifier: Programming Language :: Python :: 3.11
Classifier: Topic :: Scientific/Engineering :: Physics
Classifier: Operating System :: OS Independent
Requires-Python: >=3.11
License-File: LICENSE
Requires-Dist: numpy >=1.26
Requires-Dist: pandas >=2.1.1
Requires-Dist: periodictable >=1.6.1
Requires-Dist: scipy >=1.11.3
Requires-Dist: xarray >=2023
